Workbook

Sheet Análisis Costo-Beneficio
A1: Análisis Costo-Beneficio — TutorConnect
A2: Proyecto: TutorConnect — Plataforma Web de Tutorías Universitarias | E2: Gerente de Proyecto: | F2: Diego Andrés Becerra Bonilla
A4: PARTE 1 — Identificación y Clasificación de Costos
A5: Elemento | B5: Clasificación | C5: Descripción / Justificación
A6: a) Salarios de desarrolladores y equipo | B6: Costo Directo | C6: Recurso humano principal del proyecto; asociado directamente al desarrollo del MVP académico.
A7: b) Servicio de internet y conectividad | B7: Costo Indirecto | C7: Infraestructura compartida; no es exclusiva del proyecto TutorConnect.
A8: c) Hosting y servicios cloud (Docker, servidor) | B8: Costo de Operación | C8: Gasto recurrente una vez la plataforma esté desplegada en producción.
A9: d) Corrección de errores post-entrega | B9: Costo de Mantenimiento | C9: Ocurre después de la entrega; garantiza la calidad continua del sistema.
A10: e) Licencias y herramientas de desarrollo | B10: Costo Directo | C10: IDE, repositorio Git, herramientas de análisis estático y despliegue.
A12: PARTE 2 — Estimación del Costo del Proyecto (16 semanas / 4 meses)
A13: Recurso / Concepto | B13: Cantidad | C13: Costo Mensual (COP) | D13: Mes 1 | E13: Mes 2 | F13: Mes 3 | G13: Mes 4 | H13: Total (COP)
A14: Analistas / Scrum Master | B14: 1 | C14: 1500000 | D14: =B14*C14 -> 1500000 | E14: =B14*C14 -> 1500000 | F14: =B14*C14 -> 1500000 | G14: =B14*C14 -> 1500000 | H14: =SUM(D14:G14) -> 6000000
A15: Desarrolladores Backend | B15: 2 | C15: 2000000 | D15: =B15*C15 -> 4000000 | E15: =B15*C15 -> 4000000 | F15: =B15*C15 -> 4000000 | G15: =B15*C15 -> 4000000 | H15: =SUM(D15:G15) -> 16000000
A16: Desarrolladores Frontend | B16: 2 | C16: 2000000 | D16: =B16*C16 -> 4000000 | E16: =B16*C16 -> 4000000 | F16: =B16*C16 -> 4000000 | G16: =B16*C16 -> 4000000 | H16: =SUM(D16:G16) -> 16000000
A17: Tester / QA | B17: 1 | C17: 1500000 | D17: =B17*C17 -> 1500000 | E17: =B17*C17 -> 1500000 | F17: =B17*C17 -> 1500000 | G17: =B17*C17 -> 1500000 | H17: =SUM(D17:G17) -> 6000000
A18: Total Personal | D18: =SUM(D14:D17) -> 11000000 | E18: =SUM(E14:E17) -> 11000000 | F18: =SUM(F14:F17) -> 11000000 | G18: =SUM(G14:G17) -> 11000000 | H18: =SUM(H14:H17) -> 44000000
A19: Servicio SMTP / correo (12 meses) | H19: 1440000
A20: Hosting y servidor cloud (12 meses) | H20: 7200000
A21: Dominio y certificado SSL | H21: 180000
A22: Licencias de herramientas (GitHub, SonarQube) | H22: 0
A23: Equipos / Hardware (uso del equipo) | H23: 0
A24: Contingencia (10% del total personal) | H24: =H18*0.1 -> 4400000
A25: COSTO TOTAL DEL PROYECTO | H25: =H18+SUM(H19:H24) -> 57220000
A27: PARTE 3 — Análisis Costo-Beneficio (Proyección 5 Años)
A28: Concepto | B28: Valor (COP) | C28: Año 1 | D28: Año 2 | E28: Año 3 | F28: Año 4 | G28: Año 5 | H28: Total 5 Años
A29: Inversión Total (Costo del Proyecto) | B29: =H25 -> 57220000 | C29: =H25 -> 57220000 | D29: 0 | E29: 0 | F29: 0 | G29: 0 | H29: =H25 -> 57220000
A30: Beneficio Bruto Anual Estimado | B30: 22200000 | C30: =$B30 -> 22200000 | D30: =$B30 -> 22200000 | E30: =$B30 -> 22200000 | F30: =$B30 -> 22200000 | G30: =$B30 -> 22200000 | H30: =SUM(C30:G30) -> 111000000
A31: Beneficio Neto Anual | B31: 0 | C31: =C30-C29 -> -35020000 | D31: =D30 -> 22200000 | E31: =E30 -> 22200000 | F31: =F30 -> 22200000 | G31: =G30 -> 22200000 | H31: =SUM(C31:G31) -> 53780000
A33: PARTE 4 — Indicadores Económicos
A34: Indicador | B34: Fórmula | C34: Valor Calculado | D34: Interpretación
A35: ROI (Retorno sobre Inversión) | B35: (Beneficio 5A − Inversión) / Inversión × 100 | C35: =(H30-H29)/H29 -> 0.93988116 | D35: ROI positivo a partir del año 2. En 5 años el proyecto genera un retorno significativo sobre la inversión académica inicial.
A36: Payback (Período de Recuperación) | B36: Inversión / Beneficio Anual | C36: =H29/B30 -> 2.5774775 | D36: La inversión se recupera en aproximadamente 1.5 años desde el inicio de operación del sistema TutorConnect.
A37: Beneficio Neto Acumulado (5 años) | B37: Σ Beneficios − Inversión Total | C37: =H31 -> 53780000 | D37: En 5 años el beneficio neto acumulado supera ampliamente la inversión inicial del proyecto universitario.
A39: PARTE 5 — Toma de Decisiones
A40: Pregunta | B40: Respuesta
A41: Riesgo más crítico | B41: Abandono de un integrante clave del equipo de desarrollo: detiene el avance, eleva los costos y compromete los plazos de la entrega académica. Es el más difícil de mitigar en el corto plazo, ya que el conocimiento técnico del sistema TutorConnect está concentrado en personas específicas.
A42: Beneficios tangibles (2) | B42: 1) Reducción del tiempo invertido en coordinar tutorías (elimina procesos manuales via WhatsApp o tablones físicos). 2) Disminución de incidencias por agendamientos duplicados o sin respuesta, reduciendo la deserción en el uso de tutorías académicas.
A43: Beneficios intangibles (2) | B43: 1) Mejora de la imagen institucional de la universidad al contar con una plataforma digital moderna de apoyo académico. 2) Mayor satisfacción y motivación de los estudiantes al tener acceso fácil y rápido a tutores especializados en sus asignaturas.
A44: Alternativa SaaS ($150.000/mes) | B44: Sí se evalúa como alternativa. Costo anual SaaS: ~$1.8M COP/año. En 5 años el desarrollo propio resulta significativamente más económico y permite mayor personalización al contexto universitario. La solución SaaS implicaría dependencia del proveedor y limitaciones para adaptarse a los requerimientos académicos específicos del proyecto.

Sheet Dashboard
A1: DASHBOARD — Proyección Financiera del Proyecto TutorConnect
A2: Resumen Ejecutivo del Análisis Económico
A4: Inversión Total (COP) | C4: Beneficio Anual (COP) | E4: ROI (5 Años) (%) | G4: Payback (años)
A5: ='Análisis Costo-Beneficio'!H25 -> 57220000 | C5: ='Análisis Costo-Beneficio'!B30 -> 22200000 | E5: ='Análisis Costo-Beneficio'!C35 -> 0.93988116 | G5: ='Análisis Costo-Beneficio'!C36 -> 2.5774775
A8: Proyección de Beneficio Neto Acumulado — 5 Años
A9: Concepto | B9: Año 1 | C9: Año 2 | D9: Año 3 | E9: Año 4 | F9: Año 5 | G9: Total | H9: Notas
A10: Inversión / Egreso | B10: ='Análisis Costo-Beneficio'!H25 -> 57220000 | C10: 0 | D10: 0 | E10: 0 | F10: 0 | G10: ='Análisis Costo-Beneficio'!H25 -> 57220000 | H10: Inversión única en el año inicial
A11: Beneficio Bruto Anual | B11: ='Análisis Costo-Beneficio'!B30 -> 22200000 | C11: ='Análisis Costo-Beneficio'!B30 -> 22200000 | D11: ='Análisis Costo-Beneficio'!B30 -> 22200000 | E11: ='Análisis Costo-Beneficio'!B30 -> 22200000 | F11: ='Análisis Costo-Beneficio'!B30 -> 22200000 | G11: ='Análisis Costo-Beneficio'!H30 -> 111000000 | H11: Ahorro institucional estimado anual
A12: Beneficio Neto Anual | B12: =B11-B10 -> -35020000 | C12: =C11-C10 -> 22200000 | D12: =D11-D10 -> 22200000 | E12: =E11-E10 -> 22200000 | F12: =F11-F10 -> 22200000 | G12: =SUM(B12:F12) -> 53780000 | H12: Beneficio anual menos la inversión
A13: Beneficio Acumulado | B13: =B12 -> -35020000 | C13: =C12+B13 -> -12820000 | D13: =D12+C13 -> 9380000 | E13: =E12+D13 -> 31580000 | F13: =F12+E13 -> 53780000 | G13: =F13 -> 53780000 | H13: Suma acumulada del beneficio neto
A15: Comparativa: Desarrollo Propio vs. Solución SaaS ($150.000/mes)
A16: Escenario | B16: Año 1 | C16: Año 2 | D16: Año 3 | E16: Año 4 | F16: Año 5 | G16: Costo Total 5A | H16: Diferencia
A17: Desarrollo Propio | B17: ='Análisis Costo-Beneficio'!H25 -> 57220000 | C17: 0 | D17: 0 | E17: 0 | F17: 0 | G17: =SUM(B17:F17) -> 57220000
A18: Solución SaaS ($150.000/mes) | B18: 1800000 | C18: 1800000 | D18: 1800000 | E18: 1800000 | F18: 1800000 | G18: =SUM(B18:F18) -> 9000000
A19: Ahorro al elegir Desarrollo Propio vs SaaS en 5 años: | G19: =G18-G17 -> -48220000 | H19: SaaS cuesta más en 5 años
A21: Gestión de Riesgos Identificados
A22: # | B22: Riesgo | C22: Nivel | D22: Impacto | E22: Estrategia de Mitigación
A23: 1 | B23: Cambios frecuentes de requisitos académicos | C23: ALTO | D23: Retrasos y sobrecostos | E23: Aplicar Scrum; definir proceso formal de gestión de cambios con aprobación del docente y del equipo.
A24: 2 | B24: Retrasos en el desarrollo del MVP | C24: MEDIO | D24: Incumplimiento de plazos | E24: Seguimiento semanal con tablero Kanban; identificar cuellos de botella en los daily stand-ups.
A25: 3 | B25: Abandono de un integrante clave | C25: CRÍTICO | D25: Paralización del proyecto | E25: Documentar código continuamente; fomentar pair programming y transferencia de conocimiento entre todos los miembros.
A26: 4 | B26: Vulnerabilidades de seguridad | C26: MEDIO | D26: Exposición de datos de usuarios | E26: Ejecutar npm audit en cada sprint; revisión de seguridad en la semana 12 antes del release final.
A27: 5 | B27: Fallo del servicio SMTP en producción | C27: BAJO | D27: Pérdida de notificaciones | E27: Implementar cola de reintentos; monitorear cuota del proveedor SMTP; tener proveedor alternativo identificado.
